[{"id":"8ce0b4b0-5dd0-43ae-b251-ad674ac6f0b7","lines":[{"description":"SKU-1063 x 1","price":{"GBP":14.99}},{"description":"SKU-1053 x 1","price":{"GBP":14.99}},{"description":"SKU-1019 x 1","price":{"GBP":14.99}},{"description":"SKU-1070 x 1","price":{"GBP":14.99}},{"description":"Delivery","price":{"GBP":3.49}}],"date":{"date":"2016-07-18T01:43:52.000Z"},"total":{"GBP":63.45},"invoice-address":["9","Blue Anchor Court","Hemel Hempstead","HP2 4KU"],"delivery-address":["9","Blue Anchor Court","Hemel Hempstead","HP2 4KU"]},{"id":"1dbe5392-d322-46e8-8459-d5f2f7610711","lines":[{"description":"SKU-1040 x 1","price":{"GBP":14.99}},{"description":"SKU-1063 x 1","price":{"GBP":14.99}},{"description":"SKU-1038 x 1","price":{"GBP":14.99}},{"description":"SKU-1065 x 1","price":{"GBP":14.99}},{"description":"SKU-1084 x 1","price":{"GBP":14.99}},{"description":"Delivery","price":{"GBP":3.49}}],"date":{"date":"2016-07-18T02:04:00.000Z"},"total":{"GBP":78.44},"invoice-address":["14","Shavers Place","Coventry","CV19 6NR"],"delivery-address":["14","Shavers Place","Coventry","CV19 6NR"]},{"id":"29ae73b7-fd60-4d52-9ec7-14859ac68d59","lines":[{"description":"SKU-1043 x 1","price":{"GBP":14.99}},{"description":"SKU-1002 x 1","price":{"GBP":14.99}},{"description":"SKU-1098 x 1","price":{"GBP":14.99}},{"description":"SKU-1060 x 1","price":{"GBP":14.99}},{"description":"Delivery","price":{"GBP":3.49}}],"date":{"date":"2016-07-18T02:24:58.000Z"},"total":{"GBP":63.45},"invoice-address":["72","Redchurch Street","Plymouth","PL15 6AW"],"delivery-address":["72","Redchurch Street","Plymouth","PL15 6AW"]},{"id":"bad3b511-8635-41b1-932f-6b7d076006e1","lines":[{"description":"SKU-1080 x 1","price":{"GBP":14.99}},{"description":"SKU-1081 x 1","price":{"GBP":14.99}},{"description":"SKU-1017 x 1","price":{"GBP":14.99}},{"description":"Delivery","price":{"GBP":3.49}}],"date":{"date":"2016-07-18T02:41:50.000Z"},"total":{"GBP":48.46},"invoice-address":["93","Salmon Buildings","Crewe","CW15 4PD"],"delivery-address":["93","Salmon Buildings","Crewe","CW15 4PD"]},{"id":"8fd3e920-9aed-47e1-8e13-d5999e2acc27","lines":[{"description":"SKU-1090 x 1","price":{"GBP":14.99}},{"description":"Delivery","price":{"GBP":3.49}}],"date":{"date":"2016-07-18T02:48:33.000Z"},"total":{"GBP":18.48},"invoice-address":["39","Albion Avenue","Falkirk","FK17 8DX"],"delivery-address":["39","Albion Avenue","Falkirk","FK17 8DX"]},{"id":"d6546f04-1e6e-4893-bffe-658c17748ef1","lines":[{"description":"SKU-1053 x 1","price":{"GBP":14.99}},{"description":"SKU-1087 x 1","price":{"GBP":14.99}},{"description":"SKU-1086 x 1","price":{"GBP":14.99}},{"description":"SKU-1019 x 1","price":{"GBP":14.99}},{"description":"SKU-1045 x 1","price":{"GBP":14.99}},{"description":"Delivery","price":{"GBP":3.49}}],"date":{"date":"2016-07-18T04:02:05.000Z"},"total":{"GBP":78.44},"invoice-address":["37","St. Thomas's Way","Motherwell","ML10 6VW"],"delivery-address":["37","St. Thomas's Way","Motherwell","ML10 6VW"]},{"id":"570611cc-e00f-41c5-873e-741e595e28ae","lines":[{"description":"SKU-1023 x 1","price":{"GBP":14.99}},{"description":"SKU-1069 x 1","price":{"GBP":14.99}},{"description":"SKU-1029 x 1","price":{"GBP":14.99}},{"description":"Delivery","price":{"GBP":3.49}}],"date":{"date":"2016-07-18T05:02:36.000Z"},"total":{"GBP":48.46},"invoice-address":["54","Parvin Street","Harrow","HA16 3LC"],"delivery-address":["54","Parvin Street","Harrow","HA16 3LC"]},{"id":"ec97d746-2c6f-4fc0-9098-140d641f2b79","lines":[{"description":"SKU-1085 x 1","price":{"GBP":14.99}},{"description":"SKU-1067 x 1","price":{"GBP":14.99}},{"description":"SKU-1036 x 1","price":{"GBP":14.99}},{"description":"Delivery","price":{"GBP":3.49}}],"date":{"date":"2016-07-18T07:50:29.000Z"},"total":{"GBP":48.46},"invoice-address":["86","Bethwin Cottages","Dorchester","DT9 1FW"],"delivery-address":["86","Bethwin Cottages","Dorchester","DT9 1FW"]},{"id":"758cd28b-ec12-4ef6-8d3f-8d52ceb9b04f","lines":[{"description":"SKU-1096 x 1","price":{"GBP":14.99}},{"description":"SKU-1040 x 1","price":{"GBP":14.99}},{"description":"Delivery","price":{"GBP":3.49}}],"date":{"date":"2016-07-18T09:39:42.000Z"},"total":{"GBP":33.47},"invoice-address":["37","Carnegie Street","Dorchester","DT11 3XY"],"delivery-address":["37","Carnegie Street","Dorchester","DT11 3XY"]},{"id":"4dd6246d-bdb2-4e30-875a-d0700985cf45","lines":[{"description":"SKU-1049 x 1","price":{"GBP":14.99}},{"description":"Delivery","price":{"GBP":3.49}}],"date":{"date":"2016-07-18T13:22:09.000Z"},"total":{"GBP":18.48},"invoice-address":["69","Spafield Street","Luton","LU11 1UA"],"delivery-address":["69","Spafield Street","Luton","LU11 1UA"]},{"id":"69b93790-6cd2-4b61-ae3a-7816ca0d894b","lines":[{"description":"SKU-1068 x 1","price":{"GBP":14.99}},{"description":"SKU-1030 x 1","price":{"GBP":14.99}},{"description":"SKU-1001 x 2","price":{"GBP":14.99}},{"description":"SKU-1037 x 1","price":{"GBP":14.99}},{"description":"Delivery","price":{"GBP":3.49}}],"date":{"date":"2016-07-18T13:44:40.000Z"},"total":{"GBP":63.45},"invoice-address":["102","Bacton Street","Harrow","HA18 7JY"],"delivery-address":["102","Bacton Street","Harrow","HA18 7JY"]},{"id":"c7d1f7e7-94d5-4e09-bf16-14693c795b62","lines":[{"description":"SKU-1048 x 1","price":{"GBP":14.99}},{"description":"SKU-1023 x 1","price":{"GBP":14.99}},{"description":"SKU-1035 x 1","price":{"GBP":14.99}},{"description":"Delivery","price":{"GBP":3.49}}],"date":{"date":"2016-07-18T14:30:56.000Z"},"total":{"GBP":48.46},"invoice-address":["66","Boot Buildings","Leeds","LS11 8RL"],"delivery-address":["66","Boot Buildings","Leeds","LS11 8RL"]},{"id":"f39814bb-5e16-47ab-8a60-a3d4286bd119","lines":[{"description":"SKU-1083 x 1","price":{"GBP":14.99}},{"description":"SKU-1011 x 1","price":{"GBP":14.99}},{"description":"SKU-1079 x 1","price":{"GBP":14.99}},{"description":"SKU-1041 x 1","price":{"GBP":14.99}},{"description":"Delivery","price":{"GBP":3.49}}],"date":{"date":"2016-07-18T15:27:34.000Z"},"total":{"GBP":63.45},"invoice-address":["7","Buckley Street","Norwich","NR2 7AC"],"delivery-address":["7","Buckley Street","Norwich","NR2 7AC"]},{"id":"8b814b36-fa92-453d-ba5b-fbbc5f1c8771","lines":[{"description":"SKU-1067 x 1","price":{"GBP":14.99}},{"description":"SKU-1070 x 1","price":{"GBP":14.99}},{"description":"SKU-1041 x 1","price":{"GBP":14.99}},{"description":"Delivery","price":{"GBP":3.49}}],"date":{"date":"2016-07-18T15:31:40.000Z"},"total":{"GBP":48.46},"invoice-address":["99","St. Luke's Mews","Bristol","BS3 3KS"],"delivery-address":["99","St. Luke's Mews","Bristol","BS3 3KS"]},{"id":"665f9a50-4698-425f-9f04-9808933c64f1","lines":[{"description":"SKU-1046 x 1","price":{"GBP":14.99}},{"description":"SKU-1015 x 1","price":{"GBP":14.99}},{"description":"SKU-1085 x 2","price":{"GBP":14.99}},{"description":"Delivery","price":{"GBP":3.49}}],"date":{"date":"2016-07-18T16:09:33.000Z"},"total":{"GBP":48.46},"invoice-address":["54","Invermore Place","Gloucester","GL12 8NK"],"delivery-address":["55","Priory Walk","West London","W13 6AR"]},{"id":"0068d142-ea81-4ff6-a6ae-492a90f9e3d2","lines":[{"description":"SKU-1048 x 1","price":{"GBP":14.99}},{"description":"SKU-1091 x 1","price":{"GBP":14.99}},{"description":"SKU-1031 x 1","price":{"GBP":14.99}},{"description":"SKU-1027 x 1","price":{"GBP":14.99}},{"description":"SKU-1047 x 1","price":{"GBP":14.99}},{"description":"Delivery","price":{"GBP":3.49}}],"date":{"date":"2016-07-18T17:51:51.000Z"},"total":{"GBP":78.44},"invoice-address":["110","Inn Yard","Walsall","WS10 1JP"],"delivery-address":["110","Inn Yard","Walsall","WS10 1JP"]},{"id":"3bb81bdd-9976-440b-b9cc-c37641801188","lines":[{"description":"SKU-1093 x 1","price":{"GBP":14.99}},{"description":"Delivery","price":{"GBP":3.49}}],"date":{"date":"2016-07-18T18:03:24.000Z"},"total":{"GBP":18.48},"invoice-address":["104","St. Mary's Gardens","Halifax","HX8 1MX"],"delivery-address":["104","St. Mary's Gardens","Halifax","HX8 1MX"]},{"id":"56cc5f43-f867-4c36-9bf3-75f7b74f17ec","lines":[{"description":"SKU-1010 x 1","price":{"GBP":14.99}},{"description":"SKU-1003 x 1","price":{"GBP":14.99}},{"description":"SKU-1030 x 1","price":{"GBP":14.99}},{"description":"Delivery","price":{"GBP":3.49}}],"date":{"date":"2016-07-18T19:46:40.000Z"},"total":{"GBP":48.46},"invoice-address":["65","Parkgate Road","Cardiff","CF13 7CQ"],"delivery-address":["65","Parkgate Road","Cardiff","CF13 7CQ"]},{"id":"5bfeee77-52e4-4247-a9c2-a63ca1e78028","lines":[{"description":"SKU-1044 x 2","price":{"GBP":14.99}},{"description":"SKU-1002 x 1","price":{"GBP":14.99}},{"description":"SKU-1057 x 1","price":{"GBP":14.99}},{"description":"SKU-1035 x 1","price":{"GBP":14.99}},{"description":"Delivery","price":{"GBP":3.49}}],"date":{"date":"2016-07-18T20:05:28.000Z"},"total":{"GBP":63.45},"invoice-address":["110","Cavaye Place","Aberdeen","AB7 7RL"],"delivery-address":["110","Cavaye Place","Aberdeen","AB7 7RL"]},{"id":"b26b6867-6895-4615-8794-cdbcf3d90a6a","lines":[{"description":"SKU-1076 x 1","price":{"GBP":14.99}},{"description":"SKU-1059 x 1","price":{"GBP":14.99}},{"description":"Delivery","price":{"GBP":3.49}}],"date":{"date":"2016-07-18T21:07:04.000Z"},"total":{"GBP":33.47},"invoice-address":["5","Ashlar Place","Chester","CH5 7VP"],"delivery-address":["5","Ashlar Place","Chester","CH5 7VP"]},{"id":"d8d6178a-e622-424a-ae1a-5d0045d49d6e","lines":[{"description":"SKU-1070 x 1","price":{"GBP":14.99}},{"description":"Delivery","price":{"GBP":3.49}}],"date":{"date":"2016-07-18T21:17:18.000Z"},"total":{"GBP":18.48},"invoice-address":["37","Varndell Street","Darlington","DL15 5AT"],"delivery-address":["37","Varndell Street","Darlington","DL15 5AT"]},{"id":"5fe48d5f-b77b-4047-8370-7bb84ff81f63","lines":[{"description":"SKU-1064 x 1","price":{"GBP":14.99}},{"description":"Delivery","price":{"GBP":3.49}}],"date":{"date":"2016-07-18T21:30:13.000Z"},"total":{"GBP":18.48},"invoice-address":["103","Eversholt Row","Romford","RM7 8LZ"],"delivery-address":["103","Eversholt Row","Romford","RM7 8LZ"]}]