[{"id":"ac2183a7-dd16-4a2a-8292-7fcb94f04cd1","order":"12e435a8-b9a6-45e9-aee6-a51439acf3d2","ordered-at":{"date":"2016-09-23T02:04:11.000Z"},"shipped-at":{"date":"2016-09-27T11:29:08.000Z"},"skus":[{"sku":"SKU-1098","quantity":1},{"sku":"SKU-1015","quantity":1},{"sku":"SKU-1100","quantity":1},{"sku":"SKU-1010","quantity":1},{"sku":"SKU-1028","quantity":2}]},{"id":"ec55413c-9c81-483d-abeb-f1e8b0ac4a7d","order":"b2e16dea-265a-42bf-973e-30026bd37cd6","ordered-at":{"date":"2016-09-23T13:51:31.000Z"},"shipped-at":{"date":"2016-09-27T17:24:24.000Z"},"skus":[{"sku":"SKU-1100","quantity":1},{"sku":"SKU-1075","quantity":1},{"sku":"SKU-1070","quantity":1},{"sku":"SKU-1077","quantity":1},{"sku":"SKU-1010","quantity":1}]},{"id":"998900f6-46f8-4970-8f98-c3fdfcf5f8f9","order":"c468c5ba-fe90-4ab5-942f-df14490af2fd","ordered-at":{"date":"2016-09-24T01:07:09.000Z"},"shipped-at":{"date":"2016-09-27T10:30:58.000Z"},"skus":[{"sku":"SKU-1064","quantity":1},{"sku":"SKU-1028","quantity":2}]},{"id":"a1839689-3028-40e2-8b03-3b74c0d7aa27","order":"478c5c0c-b515-4d44-bbab-270b3faec069","ordered-at":{"date":"2016-09-24T03:22:48.000Z"},"shipped-at":{"date":"2016-09-27T15:36:47.000Z"},"skus":[{"sku":"SKU-1057","quantity":1},{"sku":"SKU-1040","quantity":1},{"sku":"SKU-1099","quantity":1}]},{"id":"ef4c84fa-bde1-4cd5-ae01-b919c2bafb27","order":"ebb71224-3e6e-4d22-872d-24ca93a9de8d","ordered-at":{"date":"2016-09-24T23:58:26.000Z"},"shipped-at":{"date":"2016-09-27T12:38:39.000Z"},"skus":[{"sku":"SKU-1060","quantity":1}]},{"id":"0fc692a8-08ce-4bf1-88a2-aeadf1026344","order":"8a779f7d-67f9-4ffc-9969-46c01bcffb5e","ordered-at":{"date":"2016-09-25T04:27:52.000Z"},"shipped-at":{"date":"2016-09-27T14:17:43.000Z"},"skus":[{"sku":"SKU-1100","quantity":1},{"sku":"SKU-1042","quantity":1},{"sku":"SKU-1002","quantity":1},{"sku":"SKU-1097","quantity":1},{"sku":"SKU-1020","quantity":1}]},{"id":"0c70f1db-9278-4d0d-8dec-080a643b4c64","order":"28d5223a-32af-4b14-9c33-79d3107041fd","ordered-at":{"date":"2016-09-25T08:19:41.000Z"},"shipped-at":{"date":"2016-09-27T09:33:48.000Z"},"skus":[{"sku":"SKU-1029","quantity":1},{"sku":"SKU-1069","quantity":1},{"sku":"SKU-1053","quantity":1},{"sku":"SKU-1005","quantity":1}]},{"id":"452d2ce2-3ae9-46d4-b09e-0378b417b69c","order":"080df73a-6051-49f8-9957-ce290c456bcd","ordered-at":{"date":"2016-09-25T08:43:18.000Z"},"shipped-at":{"date":"2016-09-27T09:53:14.000Z"},"skus":[{"sku":"SKU-1050","quantity":1}]},{"id":"4e0da936-898a-4f1c-a4ae-7158dd45d45b","order":"904dff03-5e3f-4440-88fe-2cda51b9ebfc","ordered-at":{"date":"2016-09-25T09:01:49.000Z"},"shipped-at":{"date":"2016-09-27T11:10:55.000Z"},"skus":[{"sku":"SKU-1006","quantity":1},{"sku":"SKU-1091","quantity":1},{"sku":"SKU-1065","quantity":1}]},{"id":"d6c9737a-13c0-4caf-9055-10efd9f98862","order":"f501c363-4b9b-4b43-b1b1-a3379aaf28cb","ordered-at":{"date":"2016-09-25T10:10:02.000Z"},"shipped-at":{"date":"2016-09-27T12:26:51.000Z"},"skus":[{"sku":"SKU-1090","quantity":1},{"sku":"SKU-1030","quantity":1}]},{"id":"92034e7c-966e-4612-9ecb-004fa84d0161","order":"12641a88-b95d-4682-9249-ff4d1532cebd","ordered-at":{"date":"2016-09-25T11:54:01.000Z"},"shipped-at":{"date":"2016-09-27T09:20:30.000Z"},"skus":[{"sku":"SKU-1069","quantity":1},{"sku":"SKU-1088","quantity":1},{"sku":"SKU-1068","quantity":1}]},{"id":"5f2eea3a-16cf-4c7a-aa4b-11aa668e6e38","order":"52ca4b04-ea7a-4a7b-8717-5d96b021775e","ordered-at":{"date":"2016-09-25T13:47:05.000Z"},"shipped-at":{"date":"2016-09-27T12:38:40.000Z"},"skus":[{"sku":"SKU-1096","quantity":1},{"sku":"SKU-1078","quantity":1},{"sku":"SKU-1001","quantity":1},{"sku":"SKU-1065","quantity":1}]},{"id":"08450a3b-481f-4bda-b768-cf3180bfb63b","order":"01d5d335-1fd4-4a17-8980-066db70b2040","ordered-at":{"date":"2016-09-25T17:16:33.000Z"},"shipped-at":{"date":"2016-09-27T12:02:21.000Z"},"skus":[{"sku":"SKU-1062","quantity":1},{"sku":"SKU-1017","quantity":1},{"sku":"SKU-1035","quantity":1},{"sku":"SKU-1026","quantity":1},{"sku":"SKU-1023","quantity":1}]},{"id":"5e5d8eb6-5628-4dd1-91a0-2233cce8fddd","order":"eb704b33-d4e3-42d3-b685-1ae0e252c90b","ordered-at":{"date":"2016-09-25T18:16:38.000Z"},"shipped-at":{"date":"2016-09-27T11:22:38.000Z"},"skus":[{"sku":"SKU-1086","quantity":1},{"sku":"SKU-1027","quantity":1},{"sku":"SKU-1092","quantity":1},{"sku":"SKU-1009","quantity":2}]},{"id":"7adc52ab-b2fd-44a5-871c-e2d7f6b6b443","order":"1c7bbdff-39ab-451a-ac16-9cd0715aa09c","ordered-at":{"date":"2016-09-25T19:07:54.000Z"},"shipped-at":{"date":"2016-09-27T12:25:20.000Z"},"skus":[{"sku":"SKU-1073","quantity":1}]},{"id":"8650756f-e9cd-4264-abb0-e70cf3b143f4","order":"e3f234d1-a570-4282-a574-d647c053ef17","ordered-at":{"date":"2016-09-26T03:19:16.000Z"},"shipped-at":{"date":"2016-09-27T17:12:36.000Z"},"skus":[{"sku":"SKU-1041","quantity":1},{"sku":"SKU-1048","quantity":1},{"sku":"SKU-1079","quantity":2}]},{"id":"e9b92a89-3977-4f64-908b-e68cc88641ac","order":"98772ac6-0400-41e4-b653-243fc6abfb52","ordered-at":{"date":"2016-09-26T08:53:03.000Z"},"shipped-at":{"date":"2016-09-27T15:01:13.000Z"},"skus":[{"sku":"SKU-1037","quantity":1},{"sku":"SKU-1066","quantity":1},{"sku":"SKU-1090","quantity":1},{"sku":"SKU-1055","quantity":1}]},{"id":"89d33487-3a48-4d43-adf5-5cb55be67ae7","order":"a9ba94bc-94af-473a-a7a6-53f9e9fe7acb","ordered-at":{"date":"2016-09-26T12:30:55.000Z"},"shipped-at":{"date":"2016-09-27T11:10:22.000Z"},"skus":[{"sku":"SKU-1079","quantity":1},{"sku":"SKU-1073","quantity":1},{"sku":"SKU-1018","quantity":1}]},{"id":"80861e5f-dde7-478b-a40f-9b5df4cd0549","order":"01498d07-4186-4bd8-8be7-ea86f8a06122","ordered-at":{"date":"2016-09-26T12:51:49.000Z"},"shipped-at":{"date":"2016-09-27T15:29:32.000Z"},"skus":[{"sku":"SKU-1069","quantity":1},{"sku":"SKU-1090","quantity":1},{"sku":"SKU-1017","quantity":1}]},{"id":"6cb54153-1ddb-459e-bc2b-c3fe430945de","order":"389a60b9-5a45-4609-81de-bd35b2fc5362","ordered-at":{"date":"2016-09-26T17:28:37.000Z"},"shipped-at":{"date":"2016-09-27T12:43:08.000Z"},"skus":[{"sku":"SKU-1021","quantity":1}]},{"id":"59f4bd24-9fc0-4ee3-9a1f-96a8be844d5c","order":"6c7b468b-8efa-4472-8301-2a1a882e37c0","ordered-at":{"date":"2016-09-26T17:53:39.000Z"},"shipped-at":{"date":"2016-09-27T11:17:57.000Z"},"skus":[{"sku":"SKU-1036","quantity":1},{"sku":"SKU-1030","quantity":1},{"sku":"SKU-1061","quantity":1}]},{"id":"4209499b-0751-4dff-b01c-4e6f76f7fa2f","order":"e3e429ad-e697-4420-89ab-77ea76bfcf27","ordered-at":{"date":"2016-09-26T21:12:14.000Z"},"shipped-at":{"date":"2016-09-27T13:02:35.000Z"},"skus":[{"sku":"SKU-1009","quantity":1}]},{"id":"4bdc673a-226a-4b0c-98fe-2a13d2c9162d","order":"885c7e95-5dfc-4985-af61-e1f02a787342","ordered-at":{"date":"2016-09-26T21:42:12.000Z"},"shipped-at":{"date":"2016-09-27T17:55:58.000Z"},"skus":[{"sku":"SKU-1088","quantity":1},{"sku":"SKU-1082","quantity":1},{"sku":"SKU-1073","quantity":1},{"sku":"SKU-1050","quantity":1}]},{"id":"56574982-71b5-4e18-a0fd-2de7a3dcc0c1","order":"08b501cc-ec53-41ca-ab99-c89fe16ccbda","ordered-at":{"date":"2016-09-26T22:43:29.000Z"},"shipped-at":{"date":"2016-09-27T16:41:22.000Z"},"skus":[{"sku":"SKU-1018","quantity":1}]}]